{
  "title": "BTCUSDT.P 相關係數 (0.7~1.0) 日 K",
  "baseTradingViewSymbol": "BTCUSDT.P",
  "windowLabel": "1D x 20 根 K 線",
  "correlationRangeLabel": "0.70 ~ 1.00",
  "marketLabel": "Bitget USDT 永續合約",
  "updatedAtLocalText": "2026-04-14 18:17:04",
  "nextScheduledRefreshLocalText": "2026-04-14 18:32:04",
  "refreshIntervalMinutes": 15,
  "btcDirection": "up",
  "btcDirectionLabel": "BTC 最新日 K 上漲",
  "basePriceChangePercent": 3.7216,
  "basePriceChangeText": "+3.72%",
  "baseLastCloseText": "74495.1",
  "totalSymbolsScanned": 532,
  "matchedCount": 120,
  "directionRuleText": "只保留和 BTC 最新日 K 同方向上漲，且相關係數介於 0.70 到 1.00 的標的。",
  "results": [
    {
      "symbol": "ETHUSDT",
      "tradingViewSymbol": "ETHUSDT.P",
      "correlation": 0.9731,
      "correlationText": "0.9731",
      "priceChangePercent": 7.8585,
      "priceChangeText": "+7.86%",
      "latestClose": 2381.58,
      "latestCloseText": "2381.58",
      "directionLabel": "同方向",
      "trend": "up"
    },
    {
      "symbol": "SPXUSDT",
      "tradingViewSymbol": "SPXUSDT.P",
      "correlation": 0.96,
      "correlationText": "0.9600",
      "priceChangePercent": 7.2253,
      "priceChangeText": "+7.23%",
      "latestClose": 0.325,
      "latestCloseText": "0.325",
      "directionLabel": "同方向",
      "trend": "up"
    },
    {
      "symbol": "EWTUSDT",
      "tradingViewSymbol": "EWTUSDT.P",
      "correlation": 0.9554,
      "correlationText": "0.9554",
      "priceChangePercent": 2.4822,
      "priceChangeText": "+2.48%",
      "latestClose": 79.27,
      "latestCloseText": "79.27",
      "directionLabel": "同方向",
      "trend": "up"
    },
    {
      "symbol": "MOODENGUSDT",
      "tradingViewSymbol": "MOODENGUSDT.P",
      "correlation": 0.9549,
      "correlationText": "0.9549",
      "priceChangePercent": 5.7533,
      "priceChangeText": "+5.75%",
      "latestClose": 0.0511,
      "latestCloseText": "0.0511",
      "directionLabel": "同方向",
      "trend": "up"
    },
    {
      "symbol": "BNTUSDT",
      "tradingViewSymbol": "BNTUSDT.P",
      "correlation": 0.9541,
      "correlationText": "0.9541",
      "priceChangePercent": 5.0017,
      "priceChangeText": "+5.00%",
      "latestClose": 0.3086,
      "latestCloseText": "0.3086",
      "directionLabel": "同方向",
      "trend": "up"
    },
    {
      "symbol": "EWYUSDT",
      "tradingViewSymbol": "EWYUSDT.P",
      "correlation": 0.9505,
      "correlationText": "0.9505",
      "priceChangePercent": 3.5092,
      "priceChangeText": "+3.51%",
      "latestClose": 142.47,
      "latestCloseText": "142.47",
      "directionLabel": "同方向",
      "trend": "up"
    },
    {
      "symbol": "CAKEUSDT",
      "tradingViewSymbol": "CAKEUSDT.P",
      "correlation": 0.9499,
      "correlationText": "0.9499",
      "priceChangePercent": 4.6256,
      "priceChangeText": "+4.63%",
      "latestClose": 1.5788,
      "latestCloseText": "1.5788",
      "directionLabel": "同方向",
      "trend": "up"
    },
    {
      "symbol": "AWEUSDT",
      "tradingViewSymbol": "AWEUSDT.P",
      "correlation": 0.9499,
      "correlationText": "0.9499",
      "priceChangePercent": 2.7154,
      "priceChangeText": "+2.72%",
      "latestClose": 0.052429,
      "latestCloseText": "0.052429",
      "directionLabel": "同方向",
      "trend": "up"
    },
    {
      "symbol": "NEARUSDT",
      "tradingViewSymbol": "NEARUSDT.P",
      "correlation": 0.9479,
      "correlationText": "0.9479",
      "priceChangePercent": 3.3084,
      "priceChangeText": "+3.31%",
      "latestClose": 1.4208,
      "latestCloseText": "1.4208",
      "directionLabel": "同方向",
      "trend": "up"
    },
    {
      "symbol": "WIFUSDT",
      "tradingViewSymbol": "WIFUSDT.P",
      "correlation": 0.9448,
      "correlationText": "0.9448",
      "priceChangePercent": 5.8981,
      "priceChangeText": "+5.90%",
      "latestClose": 0.1975,
      "latestCloseText": "0.1975",
      "directionLabel": "同方向",
      "trend": "up"
    },
    {
      "symbol": "AMZNUSDT",
      "tradingViewSymbol": "AMZNUSDT.P",
      "correlation": 0.9405,
      "correlationText": "0.9405",
      "priceChangePercent": 1.3799,
      "priceChangeText": "+1.38%",
      "latestClose": 241.72,
      "latestCloseText": "241.72",
      "directionLabel": "同方向",
      "trend": "up"
    },
    {
      "symbol": "PEPEUSDT",
      "tradingViewSymbol": "PEPEUSDT.P",
      "correlation": 0.9398,
      "correlationText": "0.9398",
      "priceChangePercent": 5.0173,
      "priceChangeText": "+5.02%",
      "latestClose": 3.7006e-06,
      "latestCloseText": "0.0000037",
      "directionLabel": "同方向",
      "trend": "up"
    },
    {
      "symbol": "TSMUSDT",
      "tradingViewSymbol": "TSMUSDT.P",
      "correlation": 0.9391,
      "correlationText": "0.9391",
      "priceChangePercent": 2.66,
      "priceChangeText": "+2.66%",
      "latestClose": 378.61,
      "latestCloseText": "378.61",
      "directionLabel": "同方向",
      "trend": "up"
    },
    {
      "symbol": "ICPUSDT",
      "tradingViewSymbol": "ICPUSDT.P",
      "correlation": 0.9391,
      "correlationText": "0.9391",
      "priceChangePercent": 1.8428,
      "priceChangeText": "+1.84%",
      "latestClose": 2.487,
      "latestCloseText": "2.487",
      "directionLabel": "同方向",
      "trend": "up"
    },
    {
      "symbol": "ARBUSDT",
      "tradingViewSymbol": "ARBUSDT.P",
      "correlation": 0.9351,
      "correlationText": "0.9351",
      "priceChangePercent": 1.629,
      "priceChangeText": "+1.63%",
      "latestClose": 0.1123,
      "latestCloseText": "0.1123",
      "directionLabel": "同方向",
      "trend": "up"
    },
    {
      "symbol": "AVGOUSDT",
      "tradingViewSymbol": "AVGOUSDT.P",
      "correlation": 0.9329,
      "correlationText": "0.9329",
      "priceChangePercent": 1.4124,
      "priceChangeText": "+1.41%",
      "latestClose": 378.4,
      "latestCloseText": "378.4",
      "directionLabel": "同方向",
      "trend": "up"
    },
    {
      "symbol": "GEUSDT",
      "tradingViewSymbol": "GEUSDT.P",
      "correlation": 0.9299,
      "correlationText": "0.9299",
      "priceChangePercent": 1.8586,
      "priceChangeText": "+1.86%",
      "latestClose": 311.83,
      "latestCloseText": "311.83",
      "directionLabel": "同方向",
      "trend": "up"
    },
    {
      "symbol": "MONUSDT",
      "tradingViewSymbol": "MONUSDT.P",
      "correlation": 0.9283,
      "correlationText": "0.9283",
      "priceChangePercent": 8.2159,
      "priceChangeText": "+8.22%",
      "latestClose": 0.03609,
      "latestCloseText": "0.03609",
      "directionLabel": "同方向",
      "trend": "up"
    },
    {
      "symbol": "COWUSDT",
      "tradingViewSymbol": "COWUSDT.P",
      "correlation": 0.9273,
      "correlationText": "0.9273",
      "priceChangePercent": 4.3539,
      "priceChangeText": "+4.35%",
      "latestClose": 0.2229,
      "latestCloseText": "0.2229",
      "directionLabel": "同方向",
      "trend": "up"
    },
    {
      "symbol": "QQQUSDT",
      "tradingViewSymbol": "QQQUSDT.P",
      "correlation": 0.9265,
      "correlationText": "0.9265",
      "priceChangePercent": 1.3726,
      "priceChangeText": "+1.37%",
      "latestClose": 619.62,
      "latestCloseText": "619.62",
      "directionLabel": "同方向",
      "trend": "up"
    },
    {
      "symbol": "BRETTUSDT",
      "tradingViewSymbol": "BRETTUSDT.P",
      "correlation": 0.9253,
      "correlationText": "0.9253",
      "priceChangePercent": 5.0777,
      "priceChangeText": "+5.08%",
      "latestClose": 0.007305,
      "latestCloseText": "0.007305",
      "directionLabel": "同方向",
      "trend": "up"
    },
    {
      "symbol": "FUTUUSDT",
      "tradingViewSymbol": "FUTUUSDT.P",
      "correlation": 0.9252,
      "correlationText": "0.9252",
      "priceChangePercent": 2.5445,
      "priceChangeText": "+2.54%",
      "latestClose": 157.17,
      "latestCloseText": "157.17",
      "directionLabel": "同方向",
      "trend": "up"
    },
    {
      "symbol": "OPENUSDT",
      "tradingViewSymbol": "OPENUSDT.P",
      "correlation": 0.9246,
      "correlationText": "0.9246",
      "priceChangePercent": 5.8602,
      "priceChangeText": "+5.86%",
      "latestClose": 0.1969,
      "latestCloseText": "0.1969",
      "directionLabel": "同方向",
      "trend": "up"
    },
    {
      "symbol": "SPYUSDT",
      "tradingViewSymbol": "SPYUSDT.P",
      "correlation": 0.9228,
      "correlationText": "0.9228",
      "priceChangePercent": 1.1823,
      "priceChangeText": "+1.18%",
      "latestClose": 686.38,
      "latestCloseText": "686.38",
      "directionLabel": "同方向",
      "trend": "up"
    },
    {
      "symbol": "ZECUSDT",
      "tradingViewSymbol": "ZECUSDT.P",
      "correlation": 0.9217,
      "correlationText": "0.9217",
      "priceChangePercent": 8.4236,
      "priceChangeText": "+8.42%",
      "latestClose": 377.26,
      "latestCloseText": "377.26",
      "directionLabel": "同方向",
      "trend": "up"
    },
    {
      "symbol": "API3USDT",
      "tradingViewSymbol": "API3USDT.P",
      "correlation": 0.9214,
      "correlationText": "0.9214",
      "priceChangePercent": 2.0079,
      "priceChangeText": "+2.01%",
      "latestClose": 0.2845,
      "latestCloseText": "0.2845",
      "directionLabel": "同方向",
      "trend": "up"
    },
    {
      "symbol": "MORPHOUSDT",
      "tradingViewSymbol": "MORPHOUSDT.P",
      "correlation": 0.9196,
      "correlationText": "0.9196",
      "priceChangePercent": 5.1508,
      "priceChangeText": "+5.15%",
      "latestClose": 1.7883,
      "latestCloseText": "1.7883",
      "directionLabel": "同方向",
      "trend": "up"
    },
    {
      "symbol": "POPCATUSDT",
      "tradingViewSymbol": "POPCATUSDT.P",
      "correlation": 0.9183,
      "correlationText": "0.9183",
      "priceChangePercent": 3.7876,
      "priceChangeText": "+3.79%",
      "latestClose": 0.05179,
      "latestCloseText": "0.05179",
      "directionLabel": "同方向",
      "trend": "up"
    },
    {
      "symbol": "THETAUSDT",
      "tradingViewSymbol": "THETAUSDT.P",
      "correlation": 0.9167,
      "correlationText": "0.9167",
      "priceChangePercent": 3.6585,
      "priceChangeText": "+3.66%",
      "latestClose": 0.1785,
      "latestCloseText": "0.1785",
      "directionLabel": "同方向",
      "trend": "up"
    },
    {
      "symbol": "MUUSDT",
      "tradingViewSymbol": "MUUSDT.P",
      "correlation": 0.9159,
      "correlationText": "0.9159",
      "priceChangePercent": 5.7755,
      "priceChangeText": "+5.78%",
      "latestClose": 438.08,
      "latestCloseText": "438.08",
      "directionLabel": "同方向",
      "trend": "up"
    },
    {
      "symbol": "ASMLUSDT",
      "tradingViewSymbol": "ASMLUSDT.P",
      "correlation": 0.9136,
      "correlationText": "0.9136",
      "priceChangePercent": 3.8519,
      "priceChangeText": "+3.85%",
      "latestClose": 1527.9,
      "latestCloseText": "1527.9",
      "directionLabel": "同方向",
      "trend": "up"
    },
    {
      "symbol": "BANANAUSDT",
      "tradingViewSymbol": "BANANAUSDT.P",
      "correlation": 0.9088,
      "correlationText": "0.9088",
      "priceChangePercent": 4.1605,
      "priceChangeText": "+4.16%",
      "latestClose": 3.53,
      "latestCloseText": "3.53",
      "directionLabel": "同方向",
      "trend": "up"
    },
    {
      "symbol": "1INCHUSDT",
      "tradingViewSymbol": "1INCHUSDT.P",
      "correlation": 0.9062,
      "correlationText": "0.9062",
      "priceChangePercent": 4.0526,
      "priceChangeText": "+4.05%",
      "latestClose": 0.095,
      "latestCloseText": "0.095",
      "directionLabel": "同方向",
      "trend": "up"
    },
    {
      "symbol": "FILUSDT",
      "tradingViewSymbol": "FILUSDT.P",
      "correlation": 0.9046,
      "correlationText": "0.9046",
      "priceChangePercent": 3.9089,
      "priceChangeText": "+3.91%",
      "latestClose": 0.9038,
      "latestCloseText": "0.9038",
      "directionLabel": "同方向",
      "trend": "up"
    },
    {
      "symbol": "FARTCOINUSDT",
      "tradingViewSymbol": "FARTCOINUSDT.P",
      "correlation": 0.9043,
      "correlationText": "0.9043",
      "priceChangePercent": 18.0364,
      "priceChangeText": "+18.04%",
      "latestClose": 0.214,
      "latestCloseText": "0.214",
      "directionLabel": "同方向",
      "trend": "up"
    },
    {
      "symbol": "AERGOUSDT",
      "tradingViewSymbol": "AERGOUSDT.P",
      "correlation": 0.9042,
      "correlationText": "0.9042",
      "priceChangePercent": 0.6653,
      "priceChangeText": "+0.67%",
      "latestClose": 0.05447,
      "latestCloseText": "0.05447",
      "directionLabel": "同方向",
      "trend": "up"
    },
    {
      "symbol": "INTCUSDT",
      "tradingViewSymbol": "INTCUSDT.P",
      "correlation": 0.904,
      "correlationText": "0.9040",
      "priceChangePercent": 2.4775,
      "priceChangeText": "+2.48%",
      "latestClose": 66.18,
      "latestCloseText": "66.18",
      "directionLabel": "同方向",
      "trend": "up"
    },
    {
      "symbol": "NVDAUSDT",
      "tradingViewSymbol": "NVDAUSDT.P",
      "correlation": 0.9037,
      "correlationText": "0.9037",
      "priceChangePercent": 0.7808,
      "priceChangeText": "+0.78%",
      "latestClose": 189.74,
      "latestCloseText": "189.74",
      "directionLabel": "同方向",
      "trend": "up"
    },
    {
      "symbol": "HYPERUSDT",
      "tradingViewSymbol": "HYPERUSDT.P",
      "correlation": 0.9024,
      "correlationText": "0.9024",
      "priceChangePercent": 5.8954,
      "priceChangeText": "+5.90%",
      "latestClose": 0.0952,
      "latestCloseText": "0.0952",
      "directionLabel": "同方向",
      "trend": "up"
    },
    {
      "symbol": "SUIUSDT",
      "tradingViewSymbol": "SUIUSDT.P",
      "correlation": 0.9023,
      "correlationText": "0.9023",
      "priceChangePercent": 4.3045,
      "priceChangeText": "+4.30%",
      "latestClose": 0.9523,
      "latestCloseText": "0.9523",
      "directionLabel": "同方向",
      "trend": "up"
    },
    {
      "symbol": "PUMPUSDT",
      "tradingViewSymbol": "PUMPUSDT.P",
      "correlation": 0.8995,
      "correlationText": "0.8995",
      "priceChangePercent": 6.689,
      "priceChangeText": "+6.69%",
      "latestClose": 0.001914,
      "latestCloseText": "0.001914",
      "directionLabel": "同方向",
      "trend": "up"
    },
    {
      "symbol": "AEROUSDT",
      "tradingViewSymbol": "AEROUSDT.P",
      "correlation": 0.8978,
      "correlationText": "0.8978",
      "priceChangePercent": 3.4644,
      "priceChangeText": "+3.46%",
      "latestClose": 0.3763,
      "latestCloseText": "0.3763",
      "directionLabel": "同方向",
      "trend": "up"
    },
    {
      "symbol": "METAUSDT",
      "tradingViewSymbol": "METAUSDT.P",
      "correlation": 0.896,
      "correlationText": "0.8960",
      "priceChangePercent": 2.0492,
      "priceChangeText": "+2.05%",
      "latestClose": 640.42,
      "latestCloseText": "640.42",
      "directionLabel": "同方向",
      "trend": "up"
    },
    {
      "symbol": "USELESSUSDT",
      "tradingViewSymbol": "USELESSUSDT.P",
      "correlation": 0.8955,
      "correlationText": "0.8955",
      "priceChangePercent": 27.0855,
      "priceChangeText": "+27.09%",
      "latestClose": 0.04875,
      "latestCloseText": "0.04875",
      "directionLabel": "同方向",
      "trend": "up"
    },
    {
      "symbol": "CLANKERUSDT",
      "tradingViewSymbol": "CLANKERUSDT.P",
      "correlation": 0.895,
      "correlationText": "0.8950",
      "priceChangePercent": 2.3063,
      "priceChangeText": "+2.31%",
      "latestClose": 28.39,
      "latestCloseText": "28.39",
      "directionLabel": "同方向",
      "trend": "up"
    },
    {
      "symbol": "PNUTUSDT",
      "tradingViewSymbol": "PNUTUSDT.P",
      "correlation": 0.8948,
      "correlationText": "0.8948",
      "priceChangePercent": 7.999,
      "priceChangeText": "+8.00%",
      "latestClose": 0.04415,
      "latestCloseText": "0.04415",
      "directionLabel": "同方向",
      "trend": "up"
    },
    {
      "symbol": "MRVLUSDT",
      "tradingViewSymbol": "MRVLUSDT.P",
      "correlation": 0.893,
      "correlationText": "0.8930",
      "priceChangePercent": 2.3644,
      "priceChangeText": "+2.36%",
      "latestClose": 133.78,
      "latestCloseText": "133.78",
      "directionLabel": "同方向",
      "trend": "up"
    },
    {
      "symbol": "GOOGLUSDT",
      "tradingViewSymbol": "GOOGLUSDT.P",
      "correlation": 0.8889,
      "correlationText": "0.8889",
      "priceChangePercent": 1.9266,
      "priceChangeText": "+1.93%",
      "latestClose": 324.84,
      "latestCloseText": "324.84",
      "directionLabel": "同方向",
      "trend": "up"
    },
    {
      "symbol": "USTCUSDT",
      "tradingViewSymbol": "USTCUSDT.P",
      "correlation": 0.8888,
      "correlationText": "0.8888",
      "priceChangePercent": 0.2075,
      "priceChangeText": "+0.21%",
      "latestClose": 0.00483,
      "latestCloseText": "0.00483",
      "directionLabel": "同方向",
      "trend": "up"
    },
    {
      "symbol": "DEGENUSDT",
      "tradingViewSymbol": "DEGENUSDT.P",
      "correlation": 0.8839,
      "correlationText": "0.8839",
      "priceChangePercent": 2.5105,
      "priceChangeText": "+2.51%",
      "latestClose": 0.000735,
      "latestCloseText": "0.000735",
      "directionLabel": "同方向",
      "trend": "up"
    },
    {
      "symbol": "KMNOUSDT",
      "tradingViewSymbol": "KMNOUSDT.P",
      "correlation": 0.8834,
      "correlationText": "0.8834",
      "priceChangePercent": 4.4301,
      "priceChangeText": "+4.43%",
      "latestClose": 0.02098,
      "latestCloseText": "0.02098",
      "directionLabel": "同方向",
      "trend": "up"
    },
    {
      "symbol": "PEOPLEUSDT",
      "tradingViewSymbol": "PEOPLEUSDT.P",
      "correlation": 0.8831,
      "correlationText": "0.8831",
      "priceChangePercent": 7.8757,
      "priceChangeText": "+7.88%",
      "latestClose": 0.00715,
      "latestCloseText": "0.00715",
      "directionLabel": "同方向",
      "trend": "up"
    },
    {
      "symbol": "DOGSUSDT",
      "tradingViewSymbol": "DOGSUSDT.P",
      "correlation": 0.8826,
      "correlationText": "0.8826",
      "priceChangePercent": 6.4635,
      "priceChangeText": "+6.46%",
      "latestClose": 2.899e-05,
      "latestCloseText": "0.00002899",
      "directionLabel": "同方向",
      "trend": "up"
    },
    {
      "symbol": "AGLDUSDT",
      "tradingViewSymbol": "AGLDUSDT.P",
      "correlation": 0.8777,
      "correlationText": "0.8777",
      "priceChangePercent": 0.853,
      "priceChangeText": "+0.85%",
      "latestClose": 0.2483,
      "latestCloseText": "0.2483",
      "directionLabel": "同方向",
      "trend": "up"
    },
    {
      "symbol": "INUSDT",
      "tradingViewSymbol": "INUSDT.P",
      "correlation": 0.8744,
      "correlationText": "0.8744",
      "priceChangePercent": 5.3111,
      "priceChangeText": "+5.31%",
      "latestClose": 0.06127,
      "latestCloseText": "0.06127",
      "directionLabel": "同方向",
      "trend": "up"
    },
    {
      "symbol": "ORDERUSDT",
      "tradingViewSymbol": "ORDERUSDT.P",
      "correlation": 0.8736,
      "correlationText": "0.8736",
      "priceChangePercent": 6.005,
      "priceChangeText": "+6.00%",
      "latestClose": 0.05949,
      "latestCloseText": "0.05949",
      "directionLabel": "同方向",
      "trend": "up"
    },
    {
      "symbol": "COPPERUSDT",
      "tradingViewSymbol": "COPPERUSDT.P",
      "correlation": 0.8713,
      "correlationText": "0.8713",
      "priceChangePercent": 1.6336,
      "priceChangeText": "+1.63%",
      "latestClose": 6.097,
      "latestCloseText": "6.097",
      "directionLabel": "同方向",
      "trend": "up"
    },
    {
      "symbol": "AZTECUSDT",
      "tradingViewSymbol": "AZTECUSDT.P",
      "correlation": 0.869,
      "correlationText": "0.8690",
      "priceChangePercent": 0.6663,
      "priceChangeText": "+0.67%",
      "latestClose": 0.02115,
      "latestCloseText": "0.02115",
      "directionLabel": "同方向",
      "trend": "up"
    },
    {
      "symbol": "SAFEUSDT",
      "tradingViewSymbol": "SAFEUSDT.P",
      "correlation": 0.8668,
      "correlationText": "0.8668",
      "priceChangePercent": 2.984,
      "priceChangeText": "+2.98%",
      "latestClose": 0.1484,
      "latestCloseText": "0.1484",
      "directionLabel": "同方向",
      "trend": "up"
    },
    {
      "symbol": "LAYERUSDT",
      "tradingViewSymbol": "LAYERUSDT.P",
      "correlation": 0.8656,
      "correlationText": "0.8656",
      "priceChangePercent": 1.603,
      "priceChangeText": "+1.60%",
      "latestClose": 0.0824,
      "latestCloseText": "0.0824",
      "directionLabel": "同方向",
      "trend": "up"
    },
    {
      "symbol": "VTHOUSDT",
      "tradingViewSymbol": "VTHOUSDT.P",
      "correlation": 0.8653,
      "correlationText": "0.8653",
      "priceChangePercent": 2.2982,
      "priceChangeText": "+2.30%",
      "latestClose": 0.0005653,
      "latestCloseText": "0.0005653",
      "directionLabel": "同方向",
      "trend": "up"
    },
    {
      "symbol": "GMTUSDT",
      "tradingViewSymbol": "GMTUSDT.P",
      "correlation": 0.8649,
      "correlationText": "0.8649",
      "priceChangePercent": 1.537,
      "priceChangeText": "+1.54%",
      "latestClose": 0.01057,
      "latestCloseText": "0.01057",
      "directionLabel": "同方向",
      "trend": "up"
    },
    {
      "symbol": "XPINUSDT",
      "tradingViewSymbol": "XPINUSDT.P",
      "correlation": 0.8561,
      "correlationText": "0.8561",
      "priceChangePercent": 4.7015,
      "priceChangeText": "+4.70%",
      "latestClose": 0.0015522,
      "latestCloseText": "0.0015522",
      "directionLabel": "同方向",
      "trend": "up"
    },
    {
      "symbol": "METISUSDT",
      "tradingViewSymbol": "METISUSDT.P",
      "correlation": 0.8539,
      "correlationText": "0.8539",
      "priceChangePercent": 2.0422,
      "priceChangeText": "+2.04%",
      "latestClose": 3.098,
      "latestCloseText": "3.098",
      "directionLabel": "同方向",
      "trend": "up"
    },
    {
      "symbol": "EWJUSDT",
      "tradingViewSymbol": "EWJUSDT.P",
      "correlation": 0.8529,
      "correlationText": "0.8529",
      "priceChangePercent": 1.8086,
      "priceChangeText": "+1.81%",
      "latestClose": 88.94,
      "latestCloseText": "88.94",
      "directionLabel": "同方向",
      "trend": "up"
    },
    {
      "symbol": "PYTHUSDT",
      "tradingViewSymbol": "PYTHUSDT.P",
      "correlation": 0.8528,
      "correlationText": "0.8528",
      "priceChangePercent": 1.7778,
      "priceChangeText": "+1.78%",
      "latestClose": 0.04351,
      "latestCloseText": "0.04351",
      "directionLabel": "同方向",
      "trend": "up"
    },
    {
      "symbol": "UNHUSDT",
      "tradingViewSymbol": "UNHUSDT.P",
      "correlation": 0.8526,
      "correlationText": "0.8526",
      "priceChangePercent": 1.5808,
      "priceChangeText": "+1.58%",
      "latestClose": 312.3,
      "latestCloseText": "312.3",
      "directionLabel": "同方向",
      "trend": "up"
    },
    {
      "symbol": "GRASSUSDT",
      "tradingViewSymbol": "GRASSUSDT.P",
      "correlation": 0.8512,
      "correlationText": "0.8512",
      "priceChangePercent": 2.5986,
      "priceChangeText": "+2.60%",
      "latestClose": 0.3435,
      "latestCloseText": "0.3435",
      "directionLabel": "同方向",
      "trend": "up"
    },
    {
      "symbol": "CTKUSDT",
      "tradingViewSymbol": "CTKUSDT.P",
      "correlation": 0.85,
      "correlationText": "0.8500",
      "priceChangePercent": 2.7761,
      "priceChangeText": "+2.78%",
      "latestClose": 0.174,
      "latestCloseText": "0.174",
      "directionLabel": "同方向",
      "trend": "up"
    },
    {
      "symbol": "AUCTIONUSDT",
      "tradingViewSymbol": "AUCTIONUSDT.P",
      "correlation": 0.8498,
      "correlationText": "0.8498",
      "priceChangePercent": 1.3588,
      "priceChangeText": "+1.36%",
      "latestClose": 4.774,
      "latestCloseText": "4.774",
      "directionLabel": "同方向",
      "trend": "up"
    },
    {
      "symbol": "ARCUSDT",
      "tradingViewSymbol": "ARCUSDT.P",
      "correlation": 0.8475,
      "correlationText": "0.8475",
      "priceChangePercent": 0.624,
      "priceChangeText": "+0.62%",
      "latestClose": 0.07257,
      "latestCloseText": "0.07257",
      "directionLabel": "同方向",
      "trend": "up"
    },
    {
      "symbol": "HUSDT",
      "tradingViewSymbol": "HUSDT.P",
      "correlation": 0.8466,
      "correlationText": "0.8466",
      "priceChangePercent": 9.1518,
      "priceChangeText": "+9.15%",
      "latestClose": 0.10424,
      "latestCloseText": "0.10424",
      "directionLabel": "同方向",
      "trend": "up"
    },
    {
      "symbol": "STORJUSDT",
      "tradingViewSymbol": "STORJUSDT.P",
      "correlation": 0.8457,
      "correlationText": "0.8457",
      "priceChangePercent": 1.6495,
      "priceChangeText": "+1.65%",
      "latestClose": 0.0986,
      "latestCloseText": "0.0986",
      "directionLabel": "同方向",
      "trend": "up"
    },
    {
      "symbol": "XMRUSDT",
      "tradingViewSymbol": "XMRUSDT.P",
      "correlation": 0.8421,
      "correlationText": "0.8421",
      "priceChangePercent": 1.9199,
      "priceChangeText": "+1.92%",
      "latestClose": 350.37,
      "latestCloseText": "350.37",
      "directionLabel": "同方向",
      "trend": "up"
    },
    {
      "symbol": "MIRAUSDT",
      "tradingViewSymbol": "MIRAUSDT.P",
      "correlation": 0.8415,
      "correlationText": "0.8415",
      "priceChangePercent": 0.6105,
      "priceChangeText": "+0.61%",
      "latestClose": 0.0824,
      "latestCloseText": "0.0824",
      "directionLabel": "同方向",
      "trend": "up"
    },
    {
      "symbol": "ATOMUSDT",
      "tradingViewSymbol": "ATOMUSDT.P",
      "correlation": 0.8411,
      "correlationText": "0.8411",
      "priceChangePercent": 1.4988,
      "priceChangeText": "+1.50%",
      "latestClose": 1.754,
      "latestCloseText": "1.754",
      "directionLabel": "同方向",
      "trend": "up"
    },
    {
      "symbol": "CFGUSDT",
      "tradingViewSymbol": "CFGUSDT.P",
      "correlation": 0.8405,
      "correlationText": "0.8405",
      "priceChangePercent": 2.3202,
      "priceChangeText": "+2.32%",
      "latestClose": 0.20242,
      "latestCloseText": "0.20242",
      "directionLabel": "同方向",
      "trend": "up"
    },
    {
      "symbol": "EULUSDT",
      "tradingViewSymbol": "EULUSDT.P",
      "correlation": 0.8403,
      "correlationText": "0.8403",
      "priceChangePercent": 10.3382,
      "priceChangeText": "+10.34%",
      "latestClose": 1.142,
      "latestCloseText": "1.142",
      "directionLabel": "同方向",
      "trend": "up"
    },
    {
      "symbol": "BEAMUSDT",
      "tradingViewSymbol": "BEAMUSDT.P",
      "correlation": 0.8384,
      "correlationText": "0.8384",
      "priceChangePercent": 1.4024,
      "priceChangeText": "+1.40%",
      "latestClose": 0.00188,
      "latestCloseText": "0.00188",
      "directionLabel": "同方向",
      "trend": "up"
    },
    {
      "symbol": "0GUSDT",
      "tradingViewSymbol": "0GUSDT.P",
      "correlation": 0.8319,
      "correlationText": "0.8319",
      "priceChangePercent": 1.4159,
      "priceChangeText": "+1.42%",
      "latestClose": 0.5945,
      "latestCloseText": "0.5945",
      "directionLabel": "同方向",
      "trend": "up"
    },
    {
      "symbol": "FUSDT",
      "tradingViewSymbol": "FUSDT.P",
      "correlation": 0.8314,
      "correlationText": "0.8314",
      "priceChangePercent": 1.9612,
      "priceChangeText": "+1.96%",
      "latestClose": 0.005355,
      "latestCloseText": "0.005355",
      "directionLabel": "同方向",
      "trend": "up"
    },
    {
      "symbol": "INJUSDT",
      "tradingViewSymbol": "INJUSDT.P",
      "correlation": 0.8271,
      "correlationText": "0.8271",
      "priceChangePercent": 3.2148,
      "priceChangeText": "+3.21%",
      "latestClose": 3.018,
      "latestCloseText": "3.018",
      "directionLabel": "同方向",
      "trend": "up"
    },
    {
      "symbol": "BIOUSDT",
      "tradingViewSymbol": "BIOUSDT.P",
      "correlation": 0.825,
      "correlationText": "0.8250",
      "priceChangePercent": 5.4718,
      "priceChangeText": "+5.47%",
      "latestClose": 0.01889,
      "latestCloseText": "0.01889",
      "directionLabel": "同方向",
      "trend": "up"
    },
    {
      "symbol": "AVAXUSDT",
      "tradingViewSymbol": "AVAXUSDT.P",
      "correlation": 0.8236,
      "correlationText": "0.8236",
      "priceChangePercent": 2.3696,
      "priceChangeText": "+2.37%",
      "latestClose": 9.418,
      "latestCloseText": "9.418",
      "directionLabel": "同方向",
      "trend": "up"
    },
    {
      "symbol": "LINKUSDT",
      "tradingViewSymbol": "LINKUSDT.P",
      "correlation": 0.8235,
      "correlationText": "0.8235",
      "priceChangePercent": 4.3439,
      "priceChangeText": "+4.34%",
      "latestClose": 9.2,
      "latestCloseText": "9.2",
      "directionLabel": "同方向",
      "trend": "up"
    },
    {
      "symbol": "1000XECUSDT",
      "tradingViewSymbol": "1000XECUSDT.P",
      "correlation": 0.8227,
      "correlationText": "0.8227",
      "priceChangePercent": 2.2091,
      "priceChangeText": "+2.21%",
      "latestClose": 0.00694,
      "latestCloseText": "0.00694",
      "directionLabel": "同方向",
      "trend": "up"
    },
    {
      "symbol": "JSTUSDT",
      "tradingViewSymbol": "JSTUSDT.P",
      "correlation": 0.8225,
      "correlationText": "0.8225",
      "priceChangePercent": 2.3131,
      "priceChangeText": "+2.31%",
      "latestClose": 0.08006,
      "latestCloseText": "0.08006",
      "directionLabel": "同方向",
      "trend": "up"
    },
    {
      "symbol": "COTIUSDT",
      "tradingViewSymbol": "COTIUSDT.P",
      "correlation": 0.8206,
      "correlationText": "0.8206",
      "priceChangePercent": 2.0896,
      "priceChangeText": "+2.09%",
      "latestClose": 0.01368,
      "latestCloseText": "0.01368",
      "directionLabel": "同方向",
      "trend": "up"
    },
    {
      "symbol": "ZENUSDT",
      "tradingViewSymbol": "ZENUSDT.P",
      "correlation": 0.8204,
      "correlationText": "0.8204",
      "priceChangePercent": 2.0261,
      "priceChangeText": "+2.03%",
      "latestClose": 5.942,
      "latestCloseText": "5.942",
      "directionLabel": "同方向",
      "trend": "up"
    },
    {
      "symbol": "LSKUSDT",
      "tradingViewSymbol": "LSKUSDT.P",
      "correlation": 0.8177,
      "correlationText": "0.8177",
      "priceChangePercent": 2.5539,
      "priceChangeText": "+2.55%",
      "latestClose": 0.1285,
      "latestCloseText": "0.1285",
      "directionLabel": "同方向",
      "trend": "up"
    },
    {
      "symbol": "VVVUSDT",
      "tradingViewSymbol": "VVVUSDT.P",
      "correlation": 0.8156,
      "correlationText": "0.8156",
      "priceChangePercent": 11.0978,
      "priceChangeText": "+11.10%",
      "latestClose": 9.28,
      "latestCloseText": "9.28",
      "directionLabel": "同方向",
      "trend": "up"
    },
    {
      "symbol": "LITUSDT",
      "tradingViewSymbol": "LITUSDT.P",
      "correlation": 0.8156,
      "correlationText": "0.8156",
      "priceChangePercent": 1.3761,
      "priceChangeText": "+1.38%",
      "latestClose": 1.105,
      "latestCloseText": "1.105",
      "directionLabel": "同方向",
      "trend": "up"
    },
    {
      "symbol": "DEEPUSDT",
      "tradingViewSymbol": "DEEPUSDT.P",
      "correlation": 0.8152,
      "correlationText": "0.8152",
      "priceChangePercent": 2.7539,
      "priceChangeText": "+2.75%",
      "latestClose": 0.02873,
      "latestCloseText": "0.02873",
      "directionLabel": "同方向",
      "trend": "up"
    },
    {
      "symbol": "VANAUSDT",
      "tradingViewSymbol": "VANAUSDT.P",
      "correlation": 0.8143,
      "correlationText": "0.8143",
      "priceChangePercent": 0.9382,
      "priceChangeText": "+0.94%",
      "latestClose": 1.291,
      "latestCloseText": "1.291",
      "directionLabel": "同方向",
      "trend": "up"
    },
    {
      "symbol": "NMRUSDT",
      "tradingViewSymbol": "NMRUSDT.P",
      "correlation": 0.8134,
      "correlationText": "0.8134",
      "priceChangePercent": 1.6235,
      "priceChangeText": "+1.62%",
      "latestClose": 8.701,
      "latestCloseText": "8.701",
      "directionLabel": "同方向",
      "trend": "up"
    },
    {
      "symbol": "BABAUSDT",
      "tradingViewSymbol": "BABAUSDT.P",
      "correlation": 0.8123,
      "correlationText": "0.8123",
      "priceChangePercent": 1.0771,
      "priceChangeText": "+1.08%",
      "latestClose": 127.63,
      "latestCloseText": "127.63",
      "directionLabel": "同方向",
      "trend": "up"
    },
    {
      "symbol": "ENJUSDT",
      "tradingViewSymbol": "ENJUSDT.P",
      "correlation": 0.8109,
      "correlationText": "0.8109",
      "priceChangePercent": 12.1366,
      "priceChangeText": "+12.14%",
      "latestClose": 0.0486,
      "latestCloseText": "0.0486",
      "directionLabel": "同方向",
      "trend": "up"
    },
    {
      "symbol": "PROMUSDT",
      "tradingViewSymbol": "PROMUSDT.P",
      "correlation": 0.8062,
      "correlationText": "0.8062",
      "priceChangePercent": 2.751,
      "priceChangeText": "+2.75%",
      "latestClose": 1.3446,
      "latestCloseText": "1.3446",
      "directionLabel": "同方向",
      "trend": "up"
    },
    {
      "symbol": "POWRUSDT",
      "tradingViewSymbol": "POWRUSDT.P",
      "correlation": 0.8058,
      "correlationText": "0.8058",
      "priceChangePercent": 1.5577,
      "priceChangeText": "+1.56%",
      "latestClose": 0.0665,
      "latestCloseText": "0.0665",
      "directionLabel": "同方向",
      "trend": "up"
    },
    {
      "symbol": "NEIROCTOUSDT",
      "tradingViewSymbol": "NEIROCTOUSDT.P",
      "correlation": 0.8053,
      "correlationText": "0.8053",
      "priceChangePercent": 11.0526,
      "priceChangeText": "+11.05%",
      "latestClose": 6.33e-05,
      "latestCloseText": "0.0000633",
      "directionLabel": "同方向",
      "trend": "up"
    },
    {
      "symbol": "MAVUSDT",
      "tradingViewSymbol": "MAVUSDT.P",
      "correlation": 0.8049,
      "correlationText": "0.8049",
      "priceChangePercent": 3.3404,
      "priceChangeText": "+3.34%",
      "latestClose": 0.01454,
      "latestCloseText": "0.01454",
      "directionLabel": "同方向",
      "trend": "up"
    },
    {
      "symbol": "WOOUSDT",
      "tradingViewSymbol": "WOOUSDT.P",
      "correlation": 0.8045,
      "correlationText": "0.8045",
      "priceChangePercent": 5.585,
      "priceChangeText": "+5.58%",
      "latestClose": 0.01796,
      "latestCloseText": "0.01796",
      "directionLabel": "同方向",
      "trend": "up"
    },
    {
      "symbol": "LQTYUSDT",
      "tradingViewSymbol": "LQTYUSDT.P",
      "correlation": 0.8017,
      "correlationText": "0.8017",
      "priceChangePercent": 2.9315,
      "priceChangeText": "+2.93%",
      "latestClose": 0.2809,
      "latestCloseText": "0.2809",
      "directionLabel": "同方向",
      "trend": "up"
    },
    {
      "symbol": "PUNDIXUSDT",
      "tradingViewSymbol": "PUNDIXUSDT.P",
      "correlation": 0.7997,
      "correlationText": "0.7997",
      "priceChangePercent": 2.3595,
      "priceChangeText": "+2.36%",
      "latestClose": 0.1475,
      "latestCloseText": "0.1475",
      "directionLabel": "同方向",
      "trend": "up"
    },
    {
      "symbol": "MUBARAKUSDT",
      "tradingViewSymbol": "MUBARAKUSDT.P",
      "correlation": 0.7988,
      "correlationText": "0.7988",
      "priceChangePercent": 3.2838,
      "priceChangeText": "+3.28%",
      "latestClose": 0.01321,
      "latestCloseText": "0.01321",
      "directionLabel": "同方向",
      "trend": "up"
    },
    {
      "symbol": "KWEBUSDT",
      "tradingViewSymbol": "KWEBUSDT.P",
      "correlation": 0.7983,
      "correlationText": "0.7983",
      "priceChangePercent": 0.7322,
      "priceChangeText": "+0.73%",
      "latestClose": 28.616,
      "latestCloseText": "28.616",
      "directionLabel": "同方向",
      "trend": "up"
    },
    {
      "symbol": "CSCOUSDT",
      "tradingViewSymbol": "CSCOUSDT.P",
      "correlation": 0.798,
      "correlationText": "0.7980",
      "priceChangePercent": 0.4538,
      "priceChangeText": "+0.45%",
      "latestClose": 81.91,
      "latestCloseText": "81.91",
      "directionLabel": "同方向",
      "trend": "up"
    },
    {
      "symbol": "FLOCKUSDT",
      "tradingViewSymbol": "FLOCKUSDT.P",
      "correlation": 0.7962,
      "correlationText": "0.7962",
      "priceChangePercent": 2.2719,
      "priceChangeText": "+2.27%",
      "latestClose": 0.05537,
      "latestCloseText": "0.05537",
      "directionLabel": "同方向",
      "trend": "up"
    },
    {
      "symbol": "SOMIUSDT",
      "tradingViewSymbol": "SOMIUSDT.P",
      "correlation": 0.7949,
      "correlationText": "0.7949",
      "priceChangePercent": 1.5873,
      "priceChangeText": "+1.59%",
      "latestClose": 0.1664,
      "latestCloseText": "0.1664",
      "directionLabel": "同方向",
      "trend": "up"
    },
    {
      "symbol": "ZKPUSDT",
      "tradingViewSymbol": "ZKPUSDT.P",
      "correlation": 0.7941,
      "correlationText": "0.7941",
      "priceChangePercent": 2.8692,
      "priceChangeText": "+2.87%",
      "latestClose": 0.07314,
      "latestCloseText": "0.07314",
      "directionLabel": "同方向",
      "trend": "up"
    },
    {
      "symbol": "MAGICUSDT",
      "tradingViewSymbol": "MAGICUSDT.P",
      "correlation": 0.7921,
      "correlationText": "0.7921",
      "priceChangePercent": 3.8662,
      "priceChangeText": "+3.87%",
      "latestClose": 0.06179,
      "latestCloseText": "0.06179",
      "directionLabel": "同方向",
      "trend": "up"
    },
    {
      "symbol": "VELODROMEUSDT",
      "tradingViewSymbol": "VELODROMEUSDT.P",
      "correlation": 0.7904,
      "correlationText": "0.7904",
      "priceChangePercent": 1.241,
      "priceChangeText": "+1.24%",
      "latestClose": 0.015337,
      "latestCloseText": "0.015337",
      "directionLabel": "同方向",
      "trend": "up"
    },
    {
      "symbol": "HYPEUSDT",
      "tradingViewSymbol": "HYPEUSDT.P",
      "correlation": 0.7886,
      "correlationText": "0.7886",
      "priceChangePercent": 5.8296,
      "priceChangeText": "+5.83%",
      "latestClose": 44.876,
      "latestCloseText": "44.876",
      "directionLabel": "同方向",
      "trend": "up"
    },
    {
      "symbol": "SAPIENUSDT",
      "tradingViewSymbol": "SAPIENUSDT.P",
      "correlation": 0.7885,
      "correlationText": "0.7885",
      "priceChangePercent": 0.1361,
      "priceChangeText": "+0.14%",
      "latestClose": 0.07355,
      "latestCloseText": "0.07355",
      "directionLabel": "同方向",
      "trend": "up"
    },
    {
      "symbol": "GWEIUSDT",
      "tradingViewSymbol": "GWEIUSDT.P",
      "correlation": 0.7883,
      "correlationText": "0.7883",
      "priceChangePercent": 1.7852,
      "priceChangeText": "+1.79%",
      "latestClose": 0.06614,
      "latestCloseText": "0.06614",
      "directionLabel": "同方向",
      "trend": "up"
    },
    {
      "symbol": "BOMEUSDT",
      "tradingViewSymbol": "BOMEUSDT.P",
      "correlation": 0.7879,
      "correlationText": "0.7879",
      "priceChangePercent": 5.233,
      "priceChangeText": "+5.23%",
      "latestClose": 0.0004223,
      "latestCloseText": "0.0004223",
      "directionLabel": "同方向",
      "trend": "up"
    },
    {
      "symbol": "AVAUSDT",
      "tradingViewSymbol": "AVAUSDT.P",
      "correlation": 0.7877,
      "correlationText": "0.7877",
      "priceChangePercent": 2.3529,
      "priceChangeText": "+2.35%",
      "latestClose": 0.2088,
      "latestCloseText": "0.2088",
      "directionLabel": "同方向",
      "trend": "up"
    },
    {
      "symbol": "MAGMAUSDT",
      "tradingViewSymbol": "MAGMAUSDT.P",
      "correlation": 0.7871,
      "correlationText": "0.7871",
      "priceChangePercent": 8.1748,
      "priceChangeText": "+8.17%",
      "latestClose": 0.1928,
      "latestCloseText": "0.1928",
      "directionLabel": "同方向",
      "trend": "up"
    },
    {
      "symbol": "XPTUSDT",
      "tradingViewSymbol": "XPTUSDT.P",
      "correlation": 0.7867,
      "correlationText": "0.7867",
      "priceChangePercent": 1.986,
      "priceChangeText": "+1.99%",
      "latestClose": 2085.98,
      "latestCloseText": "2085.98",
      "directionLabel": "同方向",
      "trend": "up"
    },
    {
      "symbol": "ELSAUSDT",
      "tradingViewSymbol": "ELSAUSDT.P",
      "correlation": 0.7866,
      "correlationText": "0.7866",
      "priceChangePercent": 1.1084,
      "priceChangeText": "+1.11%",
      "latestClose": 0.06659,
      "latestCloseText": "0.06659",
      "directionLabel": "同方向",
      "trend": "up"
    }
  ]
}